database_sanitizer/__init__.py
database_sanitizer/__main__.py
database_sanitizer/config.py
database_sanitizer/session.py
database_sanitizer/dump/__init__.py
database_sanitizer/dump/mysql.py
database_sanitizer/dump/postgres.py
database_sanitizer/sanitizers/__init__.py
database_sanitizer/sanitizers/constant.py
database_sanitizer/sanitizers/derived.py
database_sanitizer/sanitizers/string.py
database_sanitizer/sanitizers/times.py
database_sanitizer/sanitizers/user.py
database_sanitizer/utils/__init__.py
database_sanitizer/utils/mysql.py
database_sanitizer/utils/postgres.py
database_sanitizer-1.1.0.dist-info/LICENSE
database_sanitizer-1.1.0.dist-info/METADATA
database_sanitizer-1.1.0.dist-info/WHEEL
database_sanitizer-1.1.0.dist-info/entry_points.txt
database_sanitizer-1.1.0.dist-info/top_level.txt
database_sanitizer-1.1.0.dist-info/zip-safe
database_sanitizer-1.1.0.dist-info/RECORD
