Metadata-Version: 2.1
Name: database-sanitizer
Version: 1.1.0
Summary: Sanitizes contents of a database.
Home-page: https://github.com/andersinno/python-database-sanitizer
License: MIT
Platform: UNKNOWN
Requires-Dist: PyYAML (>=3.12)
Requires-Dist: six (>=1.11.0)
Provides-Extra: mysql
Requires-Dist: PyMySQL ; extra == 'mysql'
